sariDateParser/__init__.py
sariDateParser/dateParser.py
sariDateParser/lib/DateStringParsers.py
sariDateParser/lib/TestPatterns.py
sariDateParser/lib/__init__.py
sariDateParser/lib/constants.py
date_parser_sari-0.8.11.dist-info/LICENSE
date_parser_sari-0.8.11.dist-info/METADATA
date_parser_sari-0.8.11.dist-info/WHEEL
date_parser_sari-0.8.11.dist-info/top_level.txt
date_parser_sari-0.8.11.dist-info/RECORD
