Metadata-Version: 2.1
Name: date-parser-sari
Version: 0.8.11
Summary: A parser for recognising free-text dates
Home-page: https://github.com/swiss-art-research-net/bso-date-parser.git
Author: Florian Kräutli
Author-email: florian.kraeutli@uzh.ch
License: UNKNOWN
Platform: UNKNOWN
Classifier: Programming Language :: Python :: 3
Classifier: License :: OSI Approved :: MIT License
Classifier: Operating System :: OS Independent
Requires-Python: >=3.6
